url_security_scanner-0.3.1.dist-info/licenses/LICENSE
urlscanner/api.py
urlscanner/checker.py
urlscanner/cli.py
urlscanner/init.py
urlscanner/models.py
url_security_scanner-0.3.1.dist-info/METADATA
url_security_scanner-0.3.1.dist-info/WHEEL
url_security_scanner-0.3.1.dist-info/entry_points.txt
url_security_scanner-0.3.1.dist-info/top_level.txt
url_security_scanner-0.3.1.dist-info/RECORD
